{
    "ndevice": [
        "xilinx_u200_xdma", 
        "zc", 
	"zed",
        "xilinx_u250_xdma", 
        "xilinx_u280_xdma", 
        "xilinx_u280-es1_xdma", 
        "xilinx_aws-vu9p-f1-04261818", 
        "xilinx_v350-es1_xdma", 
        "xilinx:v350-es1:xdma", 
        "xilinx:u200:xdma", 
        "xilinx:u250:xdma", 
        "xilinx:u280:xdma", 
        "xilinx:u280-es1:xdma", 
        "xilinx:aws-vu9p-f1-04261818:dynamic"
    ], 
    "default_device": "xilinx_u200_qdma_201910_1", 
    "description": [
        "This is a simple Vector Add C Kernel design with 2 Stream inputs and 1 Stream output that demonstrates on how to process an input stream of data for computation in an application using multiple compute units."
    ], 
    "contributors": [
        {
            "url": "http://www.xilinx.com", 
            "group": "Xilinx"
        }
    ], 
    "launch": [
        {
            "cmd_args": "BUILD/krnl_stream_vadd.xclbin", 
            "name": "generic launch for all flows"
        }
    ], 
    "host": {
        "host_exe": "vadd_stream", 
        "compiler": {
            "sources": [
                "REPO_DIR/common/includes/xcl2"
            ], 
            "includepaths": [
                "REPO_DIR/common/includes/xcl2"
            ]
        }
    }, 
    "key_concepts": [
        "Read/Write Stream", 
        "Create/Release Stream"
    ], 
    "keywords": [
        "cl_stream", 
        "CL_STREAM_EOT", 
        "Multiple Compute Units"
    ], 
    "runtime": [
        "OpenCL"
    ], 
    "os": [
        "Linux"
    ], 
    "containers": [
        {
            "accelerators": [
                {
                    "location": "src/krnl_stream_vadd.cpp", 
                    "name": "krnl_stream_vadd", 
                    "num_compute_units": "4:vadd_1.vadd_2.vadd_3.vadd_4"
                }
            ], 
            "name": "krnl_stream_vadd"
        }
    ], 
    "name": "Stream Vector Addition (Multiple Compute Units)"
}
