{
    "runtime": ["OpenCL"],
    "example": "Critical Path (C)",
    "overview": [
        "This example shows a normal coding style which could lead to critical path issue and design will give degraded timing.  Example also contains better coding style which can improve design timing."
    ],
    "key_concepts": [ "Critical Path handling", "Improve Timing"],
    "os": [
        "Linux"
    ],
    "libs": [
        "xcl2", "bitmap"
    ],
    "containers": [
        {
            "name": "apply_watermark_GOOD", 
            "accelerators": [
                {
                    "name": "apply_watermark",      
                    "clflags" : "-DBAD_DESIGN=0",  
                    "location": "src/apply_watermark.cpp"
                }
            ]
        }
    ],
    "host_exe": "host",
    "cmd_args" : "BUILD/apply_watermark_GOOD.xclbin PROJECT/data/input.bmp PROJECT/data/golden.bmp",
    "output_files": "output.bmp",        
    "contributors" : [
        {
            "group": "Xilinx",
            "url" : "http://www.xilinx.com"
        }
    ]
}
