{
    "cmd_args": "BUILD/nearest_neighbor.xclbin", 
    "contributors": [
        {
            "url": "http://www.xilinx.com", 
            "group": "Xilinx"
        }
    ], 
    "host_exe": "loop_fusion", 
    "overview": [
        "This example will demonstrate how to fuse two loops into one to improve the performance of an OpenCL  C/C++ Kernel."
    ], 
    "includes": [
        {
            "name": "xcl2", 
            "location": "GIT_REPO_DIR/common/includes/xcl2/"
        }
    ], 
    "key_concepts": [
        "Kernel Optimization", 
        "Loop Fusion", 
        "Loop Pipelining"
    ], 
    "keywords": [
        "#pragma HLS PIPELINE"
    ], 
    "runtime": [
        "OpenCL"
    ], 
    "os": [
        "Linux"
    ], 
    "example": "Loop Fusion (C)", 
    "containers": [
        {
            "accelerators": [
                {
                    "name": "nearest_neighbor_loop_fusion", 
                    "location": "src/nearest_neighbor.cpp"
                }, 
                {
                    "name": "nearest_neighbor", 
                    "location": "src/nearest_neighbor_bad.cpp"
                }
            ], 
            "name": "nearest_neighbor"
        }
    ]
}