{
    "name": "Systolic Array Implementation (CL)", 
    "description": [
        "This is a simple example of matrix multiplication (Row x Col) to help developers learn systolic array based algorithm design. Note: Systolic array based algorithm design is well suited for FPGA."
    ],
    "ndevice": [
        "zc702_base"
    ],
    "os": [
        "Linux"
    ], 
    "runtime": [
        "OpenCL"
    ], 
    "host": {
        "host_exe": "host", 
        "compiler": {
            "sources": [
                "REPO_DIR/common/includes/xcl2"
            ], 
            "includepaths": [
                "REPO_DIR/common/includes/xcl2"
            ]
        }
    }, 
    "containers": [
        {
            "accelerators": [
                {
                    "name": "mmult", 
                    "location": "src/mmult.cl"
                }
            ], 
            "name": "mmult"
        }
    ], 
    "launch": [
        {
            "cmd_args": "BUILD/mmult.xclbin", 
            "name": "generic launch for all flows"
        }
    ], 
    "contributors": [
        {
            "url": "http://www.xilinx.com", 
            "group": "Xilinx"
        }
    ], 
    "testinfo": {
        "level_up": [
            {
                "hw": "1"
            }
        ]
    } 
}